{
  "Name": "ortomo_PreparaatContent",
  "Description": "Updates the information of the provided ortomo_PreparaatContent record",
  "HttpMethod": "PUT",
  "IsEnabled": true,
  "OrderIndex": 199,
  "CrossDomainPolicy": "PortalAliasesOnly",
  "Inputs": [
    {
      "Name": "RecordId",
      "IsDeleted": false,
      "IsEnabled": true,
      "OrderIndex": 0,
      "Parameters": {},
      "InputTypeStr": "text",
      "Validations": [
        {
          "Data": "{\"Message\":\"RecordId is required.\"}",
          "Type": "default-required",
          "IsDeleted": false,
          "IsEnabled": false,
          "OrderIndex": 0,
          "Metadata": {
            "PAP_InternalIdentifier": "Api.InputField.RequiredValidator"
          }
        }
      ]
    },
    {
      "Name": "Preparaat",
      "IsDeleted": false,
      "IsEnabled": true,
      "OrderIndex": 1,
      "Parameters": {},
      "InputTypeStr": "text",
      "Validations": [
        {
          "Data": "{\"Message\":\"Preparaat is required.\"}",
          "Type": "default-required",
          "IsDeleted": false,
          "IsEnabled": false,
          "OrderIndex": 0,
          "Metadata": {
            "PAP_InternalIdentifier": "Api.InputField.RequiredValidator"
          }
        }
      ]
    },
    {
      "Name": "CommercieleNaam",
      "IsDeleted": false,
      "IsEnabled": true,
      "OrderIndex": 2,
      "Parameters": {},
      "InputTypeStr": "text",
      "Validations": [
        {
          "Data": "{\"Message\":\"CommercieleNaam is required.\"}",
          "Type": "default-required",
          "IsDeleted": false,
          "IsEnabled": false,
          "OrderIndex": 0,
          "Metadata": {
            "PAP_InternalIdentifier": "Api.InputField.RequiredValidator"
          }
        }
      ]
    },
    {
      "Name": "Leverancier",
      "IsDeleted": false,
      "IsEnabled": true,
      "OrderIndex": 3,
      "Parameters": {},
      "InputTypeStr": "text",
      "Validations": []
    },
    {
      "Name": "Ondertitel",
      "IsDeleted": false,
      "IsEnabled": true,
      "OrderIndex": 4,
      "Parameters": {},
      "InputTypeStr": "text",
      "Validations": []
    },
    {
      "Name": "ActieveIngredienten",
      "IsDeleted": false,
      "IsEnabled": true,
      "OrderIndex": 5,
      "Parameters": {},
      "InputTypeStr": "text",
      "Validations": []
    },
    {
      "Name": "Vulstoffen",
      "IsDeleted": false,
      "IsEnabled": true,
      "OrderIndex": 6,
      "Parameters": {},
      "InputTypeStr": "text",
      "Validations": []
    },
    {
      "Name": "Eigenschappen",
      "IsDeleted": false,
      "IsEnabled": true,
      "OrderIndex": 7,
      "Parameters": {},
      "InputTypeStr": "text",
      "Validations": []
    },
    {
      "Name": "AlgemeneProductinformatie",
      "IsDeleted": false,
      "IsEnabled": true,
      "OrderIndex": 8,
      "Parameters": {},
      "InputTypeStr": "text",
      "Validations": []
    },
    {
      "Name": "Story",
      "IsDeleted": false,
      "IsEnabled": true,
      "OrderIndex": 9,
      "Parameters": {},
      "InputTypeStr": "text",
      "Validations": []
    },
    {
      "Name": "Onderzoek",
      "IsDeleted": false,
      "IsEnabled": true,
      "OrderIndex": 10,
      "Parameters": {},
      "InputTypeStr": "text",
      "Validations": []
    },
    {
      "Name": "PreparaatAfbeelding",
      "IsDeleted": false,
      "IsEnabled": true,
      "OrderIndex": 11,
      "Parameters": {},
      "InputTypeStr": "text",
      "Validations": []
    },
    {
      "Name": "SfeerAfbeelding",
      "IsDeleted": false,
      "IsEnabled": true,
      "OrderIndex": 12,
      "Parameters": {},
      "InputTypeStr": "text",
      "Validations": []
    },
    {
      "Name": "InnameAdvies",
      "IsDeleted": false,
      "IsEnabled": false,
      "OrderIndex": 13,
      "Parameters": {},
      "InputTypeStr": "text",
      "Validations": []
    },
    {
      "Name": "MaxAantalPerPreparaat",
      "IsDeleted": false,
      "IsEnabled": false,
      "OrderIndex": 14,
      "Parameters": {},
      "InputTypeStr": "text",
      "Validations": []
    },
    {
      "Name": "IngredientenDeclaratie",
      "IsDeleted": false,
      "IsEnabled": false,
      "OrderIndex": 15,
      "Parameters": {},
      "InputTypeStr": "text",
      "Validations": [
        {
          "Data": "{\"Message\":\"IngredientenDeclaratie is required.\"}",
          "Type": "default-required",
          "IsDeleted": false,
          "IsEnabled": false,
          "OrderIndex": 0,
          "Metadata": {
            "PAP_InternalIdentifier": "Api.InputField.RequiredValidator"
          }
        }
      ]
    },
    {
      "Name": "VerplichteWaarschuwingen",
      "IsDeleted": false,
      "IsEnabled": false,
      "OrderIndex": 16,
      "Parameters": {},
      "InputTypeStr": "text",
      "Validations": []
    },
    {
      "Name": "ReferentieInnameTabel",
      "IsDeleted": false,
      "IsEnabled": false,
      "OrderIndex": 17,
      "Parameters": {},
      "InputTypeStr": "text",
      "Validations": [
        {
          "Data": "{\"Message\":\"ReferentieInnameTabel is required.\"}",
          "Type": "default-required",
          "IsDeleted": false,
          "IsEnabled": false,
          "OrderIndex": 0,
          "Metadata": {
            "PAP_InternalIdentifier": "Api.InputField.RequiredValidator"
          }
        }
      ]
    },
    {
      "Name": "DefaultAantalPerPreparaat",
      "IsDeleted": false,
      "IsEnabled": false,
      "OrderIndex": 18,
      "Parameters": {},
      "InputTypeStr": "text",
      "Validations": []
    }
  ],
  "Actions": [
    {
      "ActionType": "PlantAnApp.UpdateEntity.0.ortomo_PreparaatContent",
      "OrderIndex": 0,
      "Parameters": {
        "RecordId": "[RecordId]",
        "Preparaat": "[Preparaat]",
        "CommercieleNaam": "[CommercieleNaam]",
        "Leverancier": "[Leverancier]",
        "Ondertitel": "[Ondertitel]",
        "ActieveIngredienten": "[ActieveIngredienten]",
        "Vulstoffen": "[Vulstoffen]",
        "Eigenschappen": "[Eigenschappen]",
        "AlgemeneProductinformatie": "[AlgemeneProductinformatie]",
        "Story": "[Story]",
        "Onderzoek": "[Onderzoek]",
        "PreparaatAfbeelding": "[PreparaatAfbeelding]",
        "SfeerAfbeelding": "[SfeerAfbeelding]",
        "InnameAdvies": "[InnameAdvies]",
        "DefaultAantalPerPreparaat": "[DefaultAantalPerPreparaat]",
        "IngredientenDeclaratie": "[IngredientenDeclaratie]",
        "VerplichteWaarschuwingen": "[VerplichteWaarschuwingen]",
        "ReferentieInnameTabel": "[ReferentieInnameTabel]",
        "MaxAantalPerPreparaat": "[MaxAantalPerPreparaat]"
      },
      "IsEnabled": true,
      "ExecutionType": "OnExecute",
      "Metadata": {
        "PAP_InternalIdentifier": "Api.UpdateEntity",
        "EntityIdentifier": "ortomo_PreparaatContent"
      }
    },
    {
      "ActionType": "JsonObject",
      "OrderIndex": 1,
      "Parameters": {
        "HttpCode": "200 OK",
        "Fields": [],
        "Headers": []
      },
      "IsEnabled": true,
      "ExecutionType": "OnExecute",
      "Metadata": {
        "PAP_InternalIdentifier": "Api.Response"
      }
    }
  ],
  "OnErrorActions": []
}